{
  "number": 1286,
  "type": "pr",
  "state": "closed",
  "title": "Use Clang 10",
  "body": "**Description of Change**\r\n\r\nUse Clang 10",
  "author": {
    "login": "mattleibow",
    "type": "User"
  },
  "labels": [],
  "assignees": [],
  "milestone": "v2.80.0",
  "createdAt": "2020-05-13T00:39:57",
  "updatedAt": "2020-07-09T02:18:13",
  "closedAt": "2020-05-14T22:17:30",
  "commentCount": 0,
  "reactionCount": 4,
  "draft": false,
  "mergeableState": "unknown",
  "baseBranch": "develop",
  "headBranch": "dev/clang-10",
  "additions": 5,
  "deletions": 5,
  "changedFiles": 2,
  "commits": 3,
  "reviews": []
}