{
  "number": 1964,
  "type": "issue",
  "state": "closed",
  "title": "Method \u0027CreatePlatformView\u0027 in type \u0027SkiaSharp.Views.Maui.Handlers.SKCanvasViewHandler\u0027 from assembly \u0027SkiaSharp.Views.Maui.Core, Version=2.88.0.0, Culture=neutral, PublicKeyToken=null\u0027 does not have an implementation.",
  "body": "**Description**\r\n\r\nMethod \u0027CreatePlatformView\u0027 in type \u0027SkiaSharp.Views.Maui.Handlers.SKCanvasViewHandler\u0027 from assembly \u0027SkiaSharp.Views.Maui.Core, Version=2.88.0.0, Culture=neutral, PublicKeyToken=null\u0027 does not have an implementation.\r\n\r\n**Code**\r\n\r\nMaui App that uses SkiaSharp and crashes during Startup\r\n\r\n**Expected Behavior**\r\n\r\nApplication works\r\n\r\n**Actual Behavior**\r\n\r\nApplication Crashes\r\n\r\n**Basic Information**\r\n\r\nIt seems in Maui preview 14 (which is installed on my computer, don\u0027t know how this happend because Maui is still in Preview 13)\r\nThe base Class of \r\n\r\nhttps://github.com/mono/SkiaSharp/blob/main/source/SkiaSharp.Views.Maui/SkiaSharp.Views.Maui.Core/Handlers/SKCanvasView/SKCanvasViewHandler.Windows.cs\r\nWas changed so that a CreatePlatformView method is necessary.\r\nBecause this is not implemented Maui Crashes on Startup.\r\n\r\n**Screenshots**\r\n\r\n\r\n**Reproduction Link**\r\n\r\n\r\n",
  "author": {
    "login": "inforithmics",
    "type": "User"
  },
  "labels": [],
  "assignees": [],
  "createdAt": "2022-02-25T12:47:41",
  "updatedAt": "2022-08-19T00:01:56",
  "closedAt": "2022-03-05T00:42:20",
  "commentCount": 3,
  "reactionCount": 0
}