{
  "number": 593,
  "type": "pr",
  "state": "closed",
  "title": "Revert \u0022Update the legal files\u0022",
  "body": "Reverts mono/SkiaSharp#564",
  "author": {
    "login": "mattleibow",
    "type": "User"
  },
  "labels": [],
  "assignees": [],
  "createdAt": "2018-07-26T16:01:34",
  "updatedAt": "2018-07-26T16:03:22",
  "closedAt": "2018-07-26T16:01:42",
  "commentCount": 1,
  "reactionCount": 0,
  "draft": false,
  "mergeable": false,
  "mergeableState": "dirty",
  "baseBranch": "master",
  "headBranch": "revert-564-dev/legal",
  "additions": 32,
  "deletions": 0,
  "changedFiles": 3,
  "commits": 1,
  "reviews": []
}