{
  "number": 14,
  "type": "issue",
  "state": "closed",
  "title": "Color in SVG polygon",
  "body": "Hello, \r\n\r\nI use SKSvg extended. But for an object polygon the style=\u0022fill:lime.\r\nBut the lime color is not recognized and the polygon is black.\r\nHow to specify the fill color with a given value in hexa?\r\nThx\r\nCJ",
  "author": {
    "login": "CJACQUEL",
    "type": "User"
  },
  "labels": [
    {
      "name": "area-Svg",
      "color": "0052cc"
    }
  ],
  "assignees": [],
  "milestone": "1.59.1",
  "createdAt": "2017-08-19T17:52:31",
  "updatedAt": "2017-09-04T14:43:42",
  "closedAt": "2017-09-01T21:00:02",
  "commentCount": 4,
  "reactionCount": 0,
  "engagement": {
    "syncedAt": "2026-02-06T12:27:47.9541674Z",
    "reactions": [],
    "comments": [
      {
        "id": 324135474,
        "author": "daniel-luberda",
        "body": "It\u0027s fixed with this: https://github.com/mono/SkiaSharp.Extended/pull/15",
        "createdAt": "2017-08-22T20:01:00",
        "reactions": []
      },
      {
        "id": 325036183,
        "author": "CJACQUEL",
        "body": "Hello, \r\nCould you updgrade the nuget SkiaSharp.extended with this problem solved ?\r\nThx\r\nCjacquel",
        "createdAt": "2017-08-25T21:16:09",
        "reactions": []
      },
      {
        "id": 326682744,
        "author": "mattleibow",
        "body": "@CJACQUEL This has been merged into master: 4880d05e76fd0d64d1cd5af3fe5956175fb232f2",
        "createdAt": "2017-09-01T20:59:50",
        "reactions": []
      },
      {
        "id": 326979309,
        "author": "mattleibow",
        "body": "Released: https://github.com/mono/SkiaSharp.Extended/releases/tag/v1.59.1-svg",
        "createdAt": "2017-09-04T14:43:42",
        "reactions": []
      }
    ]
  }
}