{
  "number": 395,
  "type": "issue",
  "state": "closed",
  "title": "Unable to stretch last row or column using DrawBitmapLattice or DrawBitmapNinePatch",
  "body": "## Description: \r\nThere appears to not be a way to have the last row or column be stretchable using the SKCanvas.DrawBitmapLattice or SKCanvas.DrawBitmapNinePatch methods.  I have tried this using the UWP SkiaSharp.Views NuGet package (in a Xamarin.Forms custom renderer) as well as Android, iOS, and UWP Xamarin.Forms apps using SkiaSharp.Views.Forms Nuget package.  For simplicity, a Xamarin.Forms demo app has been provided.\r\n\r\n## Demo App: \r\nhttps://github.com/baskren/SkiaSharpStretchLastRowColumnFail\r\n\r\n## Observations:\r\n1. Clone, build and run demo app for the platform of your choice\r\n2. Click [Test1] button.   Notice the position of the sliders.  This represents the start (left) and end (right) of the stretchable region.  In [Test1], the left is 0 and the right is 25.  PLEASE NOTE THAT THE FIRST COLUMN OF THE BITMAP IS STRETCHED.\r\n3. Click the [Test2] button.  Left is 1 and right is 25.  Note:  The first column is not stretched (as it should be) and the second column is stretched.\r\n4. Click the [Test 3] button.  Left is 25 and right is 49.  Note how this appears to be the symmetrical equivalent of [Test 2] in that the second to last column is stretched but the last column is not.\r\n5. Click the [Test 4] button.  Left is 25 and right is 50.  NOTE THAT THE ENTIRE BITMAP IS STRETCHED - IN OTHER WORDS, THERE ARE NO PATCHES!\r\n7.  Click on the \u0022use DrawBitmapNinePatch\u0022 switch and repeat steps 2-5.  Note that the results are the same.\r\n\r\n## Expectations:\r\n1. Tests 1 and 2 work as expected.\r\n2. Test 3 should be the case where the last column is stretched (the symmetrical equivalent of Test 1).\r\n3. Left slider 25 and right slider 48 should be the symmetrical equivalent of Test 2 (everything between 25 and the last column- but not the last column) is stretched.\r\n\r\n## Environment:\r\n### Visual Studio:\r\nMicrosoft Visual Studio Community 2017 \r\nVersion 15.4.4\r\nVisualStudio.15.Release/15.4.4\u002B27004.2009\r\nMicrosoft .NET Framework\r\nVersion 4.7.02046\r\n\r\nInstalled Version: Community\r\n\r\nVisual Basic 2017   00369-60000-00001-AA466\r\nMicrosoft Visual Basic 2017\r\n\r\nVisual C# 2017   00369-60000-00001-AA466\r\nMicrosoft Visual C# 2017\r\n\r\nVisual F# 4.1   00369-60000-00001-AA466\r\nMicrosoft Visual F# 4.1\r\n\r\nApplication Insights Tools for Visual Studio Package   8.9.00809.2\r\nApplication Insights Tools for Visual Studio\r\n\r\nASP.NET and Web Tools 2017   15.0.30925.0\r\nASP.NET and Web Tools 2017\r\n\r\nASP.NET Core Razor Language Services   1.0\r\nProvides languages services for ASP.NET Core Razor.\r\n\r\nASP.NET Web Frameworks and Tools 2017   5.2.50921.0\r\nFor additional information, visit https://www.asp.net/\r\n\r\nAzure App Service Tools v3.0.0   15.0.30915.0\r\nAzure App Service Tools v3.0.0\r\n\r\nCommon Azure Tools   1.10\r\nProvides common services for use by Azure Mobile Services and Microsoft Azure Tools.\r\n\r\nJavaScript Language Service   2.0\r\nJavaScript Language Service\r\n\r\nJavaScript Project System   2.0\r\nJavaScript Project System\r\n\r\nJavaScript UWP Project System   2.0\r\nJavaScript UWP Project System\r\n\r\nMerq   1.1.17-rc (cba4571)\r\nCommand Bus, Event Stream and Async Manager for Visual Studio extensions.\r\n\r\nMicrosoft Azure Tools   2.9\r\nMicrosoft Azure Tools for Microsoft Visual Studio 2017 - v2.9.50719.1\r\n\r\nMicrosoft Continuous Delivery Tools for Visual Studio   0.3\r\nSimplifying the configuration of continuous build integration and continuous build delivery from within the Visual Studio IDE.\r\n\r\nMicrosoft JVM Debugger   1.0\r\nProvides support for connecting the Visual Studio debugger to JDWP compatible Java Virtual Machines\r\n\r\nMicrosoft MI-Based Debugger   1.0\r\nProvides support for connecting Visual Studio to MI compatible debuggers\r\n\r\nMicrosoft Visual Studio VC Package   1.0\r\nMicrosoft Visual Studio VC Package\r\n\r\nMono Debugging for Visual Studio   4.7.4-pre (c2d89eb)\r\nSupport for debugging Mono processes with Visual Studio.\r\n\r\nNuGet Package Manager   4.4.0\r\nNuGet Package Manager in Visual Studio. For more information about NuGet, visit http://docs.nuget.org/.\r\n\r\nSQL Server Data Tools   15.1.61707.200\r\nMicrosoft SQL Server Data Tools\r\n\r\nTypeScript   2.3.5.0\r\nTypeScript tools for Visual Studio\r\n\r\nVisual Studio Code Debug Adapter Host Package   1.0\r\nInterop layer for hosting Visual Studio Code debug adapters in Visual Studio\r\n\r\nVisual Studio Tools for Universal Windows Apps   15.0.27004.2008\r\nThe Visual Studio Tools for Universal Windows apps allow you to build a single universal app experience that can reach every device running Windows 10: phone, tablet, PC, and more. It includes the Microsoft Windows 10 Software Development Kit.\r\n\r\nVisualStudio.IoT   1.0\r\nPackage with IoT components for Visual Studio\r\n\r\nVisualStudio.Mac   1.0\r\nMac Extension for Visual Studio\r\n\r\nXamarin   4.7.10.38 (34c1b6c)\r\nVisual Studio extension to enable development for Xamarin.iOS and Xamarin.Android.\r\n\r\nXamarin.Android SDK   8.0.2.1 (HEAD/c2a33d8ea)\r\nXamarin.Android Reference Assemblies and MSBuild support.\r\n\r\nXamarin.iOS and Xamarin.Mac SDK   11.3.0.47 (51128b8)\r\nXamarin.iOS and Xamarin.Mac Reference Assemblies and MSBuild support.\r\n\r\n",
  "author": {
    "login": "baskren",
    "type": "User"
  },
  "labels": [
    {
      "name": "type/bug",
      "color": "fc2929"
    },
    {
      "name": "area/SkiaSharp",
      "color": "0052cc"
    }
  ],
  "assignees": [],
  "milestone": "1.60.0",
  "createdAt": "2017-11-18T13:55:28",
  "updatedAt": "2022-08-19T18:02:13",
  "closedAt": "2017-11-30T08:07:12",
  "commentCount": 2,
  "reactionCount": 0
}