{
  "number": 982,
  "type": "issue",
  "state": "closed",
  "title": "[QUESTION] \uD83D\uDE80 Emoji causes the pdf file to be too large",
  "body": "This question from [issues/232#issuecomment-528840847](https://github.com/mono/SkiaSharp/issues/232#issuecomment-528840847)\r\n\u0060\u0060\u0060 cs\r\n// get the character code\r\n// either:\r\nvar emojiChar = StringUtilities.GetUnicodeCharacterCode(\u0022\uD83D\uDE80\u0022, SKTextEncoding.Utf32);\r\n// or:\r\nvar emojiChar = 0x1F680;\r\n\r\n// ask the font manager for a font with that character\r\nvar fontManager = SKFontManager.Default;\r\nvar emojiTypeface = fontManager.MatchCharacter(emojiChar);\r\n\r\n// draw it\r\nvar paint = new SKPaint { Typeface = emoji };\r\ncanvas.DrawText(\u0022\uD83C\uDF10 \uD83C\uDF6A \uD83C\uDF55 \uD83D\uDE80\u0022, 20, 40, paint);\r\n\u0060\u0060\u0060",
  "author": {
    "login": "inbreaks",
    "type": "User"
  },
  "labels": [],
  "assignees": [],
  "createdAt": "2019-10-16T03:22:50",
  "updatedAt": "2022-08-19T09:02:15",
  "closedAt": "2020-06-10T23:42:18",
  "commentCount": 3,
  "reactionCount": 0
}