{
  "id": "SkiaSharp.NativeAssets.WinUI",
  "latestVersion": "3.119.2-preview.2.3",
  "totalDownloads": 400943,
  "isLegacy": false,
  "versions": [
    {
      "version": "3.0.0-preview.1.8",
      "downloads": 0,
      "published": "2024-02-06T16:26:52.22+00:00"
    },
    {
      "version": "3.0.0-preview.2.1",
      "downloads": 0,
      "published": "2024-02-20T14:25:31.507+00:00"
    },
    {
      "version": "3.0.0-preview.0.132",
      "downloads": 0,
      "published": "2024-04-09T16:10:38.717+00:00"
    },
    {
      "version": "3.0.0-preview.3.1",
      "downloads": 0,
      "published": "2024-04-10T20:29:45.433+00:00"
    },
    {
      "version": "3.0.0-preview.4.1",
      "downloads": 0,
      "published": "2024-07-18T07:21:40.367+00:00"
    },
    {
      "version": "2.88.9-preview.2.2",
      "downloads": 0,
      "published": "2024-10-24T12:20:52.757+00:00"
    },
    {
      "version": "3.0.0-preview.5.4",
      "downloads": 0,
      "published": "2024-10-24T12:20:54.757+00:00"
    },
    {
      "version": "3.116.0-preview.6.1",
      "downloads": 0,
      "published": "2024-11-06T15:25:46.367+00:00"
    },
    {
      "version": "3.118.0-preview.1.2",
      "downloads": 0,
      "published": "2024-11-06T18:17:10.853+00:00"
    },
    {
      "version": "2.88.9",
      "downloads": 68427,
      "published": "2024-11-07T18:12:28.77+00:00"
    },
    {
      "version": "3.116.0",
      "downloads": 10598,
      "published": "2024-12-03T10:18:09.417+00:00"
    },
    {
      "version": "3.116.1",
      "downloads": 134100,
      "published": "2024-12-05T16:59:05.45+00:00"
    },
    {
      "version": "3.118.0-preview.2.3",
      "downloads": 0,
      "published": "2024-12-05T16:59:21.747+00:00"
    },
    {
      "version": "3.119.0-preview.1.2",
      "downloads": 0,
      "published": "2025-04-01T23:05:04.113+00:00"
    },
    {
      "version": "3.119.0-stable.1\u002B3.119.0",
      "downloads": 0,
      "published": "2025-04-29T15:32:12.42+00:00"
    },
    {
      "version": "3.119.0",
      "downloads": 70840,
      "published": "2025-04-29T15:41:44.53+00:00"
    },
    {
      "version": "3.119.1-preview.1",
      "downloads": 0,
      "published": "2025-09-08T19:18:59.033+00:00"
    },
    {
      "version": "3.119.1",
      "downloads": 48169,
      "published": "2025-09-23T21:29:51.52+00:00"
    },
    {
      "version": "3.119.2-preview.1",
      "downloads": 0,
      "published": "2025-10-14T15:54:21.08+00:00"
    },
    {
      "version": "3.119.2-preview.2.3",
      "downloads": 0,
      "published": "2026-01-26T21:27:02.89+00:00"
    }
  ],
  "syncedAt": "2026-02-04T21:25:03.3127063Z"
}